pokemonCardLogger/__init__.py
pokemonCardLogger/assets.py
pokemonCardLogger/backup.py
pokemonCardLogger/clss_base.py
pokemonCardLogger/clss_pickle.py
pokemonCardLogger/main.py
pokemonCardLogger/packRef.py
pokemonCardLogger/test_api_status.py
pokemonCardLogger-0.2.23.dist-info/LICENSE
pokemonCardLogger-0.2.23.dist-info/METADATA
pokemonCardLogger-0.2.23.dist-info/WHEEL
pokemonCardLogger-0.2.23.dist-info/top_level.txt
pokemonCardLogger-0.2.23.dist-info/RECORD
